tkz/__init__.py
tkz/tkz.py
tkz/examples/test_basic.py
tkz/examples/test_hexbin.py
tkz/examples/test_range.py
tkz/testing/test_draw_coord.py
tkz/testing/test_hexagon_vertices.py
tkz/testing/test_hexagons.py
tkz/testing/test_memory.py
tkz/testing/test_only_y.py
tkz/testing/test_precision.py
tkz-1.0.12.dist-info/LICENSE.txt
tkz-1.0.12.dist-info/METADATA
tkz-1.0.12.dist-info/WHEEL
tkz-1.0.12.dist-info/top_level.txt
tkz-1.0.12.dist-info/RECORD
