Metadata-Version: 2.1
Name: tkz
Version: 1.0.12
Summary: TikZ Figure Generator
Author-email: David Woodburn <david.woodburn@icloud.com>
License: MIT
Project-URL: Homepage, https://gitlab.com/davidwoodburn/tkz
Project-URL: Bug Tracker, https://gitlab.com/davidwoodburn/tkz/-/issues
Classifier: Programming Language :: Python :: 3
Classifier: License :: OSI Approved :: MIT License
Classifier: Operating System :: OS Independent
Requires-Python: >=3.6
License-File: LICENSE.txt
Requires-Dist: numpy
